getpwd/__init__.py
getpwd/getpwd.py
getpwd-0.1.0.dist-info/METADATA
getpwd-0.1.0.dist-info/WHEEL
getpwd-0.1.0.dist-info/top_level.txt
getpwd-0.1.0.dist-info/RECORD
