Metadata-Version: 2.1
Name: getpwd
Version: 0.1.0
Summary: Python tool to get a password from the user and display a masked value at the prompt.
Home-page: https://github.com/rafpyprog/pyssword
Author: Rafael Alves Ribeiro
Author-email: rafael.alves.ribeiro@gmail.com
License: MIT
Keywords: getch password mask
Platform: UNKNOWN
Requires-Python: >=3.4
Requires-Dist: readchar (==2.0.1)
